README.md
pyproject.toml
setup.py
openiap/__init__.py
openiap/main.py
openiap/lib/bootstrap-linux-arm64.so
openiap/lib/bootstrap-linux-musl-arm64.so
openiap/lib/bootstrap-linux-musl-x64.so
openiap/lib/bootstrap-linux-x64.so
openiap/lib/bootstrap-macos-arm64.dylib
openiap/lib/bootstrap-macos-x64.dylib
openiap/lib/bootstrap-windows-i686.dll
openiap/lib/bootstrap-windows-x64.dll
openiap_edge.egg-info/PKG-INFO
openiap_edge.egg-info/SOURCES.txt
openiap_edge.egg-info/dependency_links.txt
openiap_edge.egg-info/top_level.txt