Metadata-Version: 2.1
Name: openiap-edge
Version: 0.0.40
Summary: Simple openiap api wrapper using proto
Home-page: https://github.com/openiap/pyapi
Author: OpenIAP ApS / Allan Zimmerman
Author-email: OpenIAP ApS / Allan Zimmerman <info@openiap.io>
Project-URL: Homepage, https://github.com/openiap/rustapi/tree/main/python
Project-URL: Bug Tracker, https://discourse.openiap.io/c/issues-and-feature-requests
Project-URL: Funding, https://github.com/sponsors/skadefro
Classifier: Programming Language :: Python :: 3
Classifier: License :: OSI Approved :: Mozilla Public License 2.0 (MPL 2.0)
Classifier: Operating System :: OS Independent
